mrpacker.cpython-311-darwin.so
mrpacker-1.15.dist-info/RECORD
mrpacker-1.15.dist-info/WHEEL
mrpacker-1.15.dist-info/top_level.txt
mrpacker-1.15.dist-info/LICENSE.txt
mrpacker-1.15.dist-info/METADATA
