Metadata-Version: 2.1
Name: mrpacker
Version: 1.15
Summary: Binary object packer for python
Home-page: https://github.com/MarkReedZ/mrpacker
Download-URL: https://github.com/MarkReedZ/mrpacker/archive/v1.6.tar.gz
Author: Mark Reed
Author-email: MarkReedZ@mail.com
License: MIT License
Keywords: mrpacker
Platform: any
Classifier: Development Status :: 5 - Production/Stable
Classifier: Intended Audience :: Developers
Classifier: License :: OSI Approved :: MIT License
Classifier: Programming Language :: C
Classifier: Programming Language :: Python :: 3
Classifier: Programming Language :: Python
License-File: LICENSE.txt
